sphinxcontrib_robotframework.py
sphinxcontrib_robotframework-0.8.1.dist-info/METADATA
sphinxcontrib_robotframework-0.8.1.dist-info/WHEEL
sphinxcontrib_robotframework-0.8.1.dist-info/top_level.txt
sphinxcontrib_robotframework-0.8.1.dist-info/zip-safe
sphinxcontrib_robotframework-0.8.1.dist-info/RECORD
