Metadata-Version: 2.1
Name: sphinxcontrib-robotframework
Version: 0.8.1
Summary: Robot Framework extension for Sphinx
Home-page: http://github.com/datakurre/sphinxcontrib_robotframework
Author: Asko Soukka
Author-email: asko.soukka@iki.fi
License: GPL
Platform: UNKNOWN
Requires-Dist: setuptools
Requires-Dist: Pygments (>=1.6)
Requires-Dist: Sphinx
Requires-Dist: robotframework (>=2.8.0)
Provides-Extra: docs
Requires-Dist: robotframework ; extra == 'docs'
Requires-Dist: robotframework-selenium2library ; extra == 'docs'
Requires-Dist: robotframework-selenium2screenshots[pillow] (>=0.5.0) ; extra == 'docs'
